<?xml version="1.0" encoding="UTF-8"?>
<metadata xml:lang="en"><Esri><CreaDate>20220619</CreaDate><CreaTime>22281200</CreaTime><ArcGISFormat>1.0</ArcGISFormat><SyncOnce>TRUE</SyncOnce><DataProperties><lineage><Process ToolSource="c:\program files (x86)\arcgis\desktop10.8\ArcToolbox\Toolboxes\Analysis Tools.tbx\Clip" Date="20220619" Time="222815">Clip STRUKPLATZOGDPolygon Void_Buffer02 "J:\My Drive\AIA_STUDIOFILESGIS\SHP_FINALS\Plaza_InVoid\Plaza_InVoid.shp" #</Process></lineage></DataProperties></Esri></metadata>
